linode_api4/__init__.py
linode_api4/common.py
linode_api4/errors.py
linode_api4/linode_client.py
linode_api4/login_client.py
linode_api4/paginated_list.py
linode_api4/util.py
linode_api4/objects/__init__.py
linode_api4/objects/account.py
linode_api4/objects/base.py
linode_api4/objects/database.py
linode_api4/objects/dbase.py
linode_api4/objects/domain.py
linode_api4/objects/filtering.py
linode_api4/objects/image.py
linode_api4/objects/linode.py
linode_api4/objects/lke.py
linode_api4/objects/longview.py
linode_api4/objects/networking.py
linode_api4/objects/nodebalancer.py
linode_api4/objects/object_storage.py
linode_api4/objects/profile.py
linode_api4/objects/region.py
linode_api4/objects/support.py
linode_api4/objects/tag.py
linode_api4/objects/volume.py
linode_api4_testrelease-5.55.4.dist-info/LICENSE
linode_api4_testrelease-5.55.4.dist-info/METADATA
linode_api4_testrelease-5.55.4.dist-info/WHEEL
linode_api4_testrelease-5.55.4.dist-info/top_level.txt
linode_api4_testrelease-5.55.4.dist-info/RECORD
