Metadata-Version: 2.1
Name: linode-api4-testrelease
Version: 5.55.4
Summary: The official python SDK for Linode API v4
Home-page: https://github.com/linode/linode_api4-python
Author: Linode
Author-email: developers@linode.com
License: BSD 3-Clause License
Keywords: linode cloud hosting infrastructure
Classifier: Development Status :: 5 - Production/Stable
Classifier: Intended Audience :: Developers
Classifier: Topic :: Software Development :: Libraries
Classifier: License :: OSI Approved :: BSD License
Classifier: Programming Language :: Python
Classifier: Programming Language :: Python :: 3
Classifier: Programming Language :: Python :: 3.6
Classifier: Programming Language :: Python :: 3.7
Classifier: Programming Language :: Python :: 3.8
Requires-Python: >=3.6
License-File: LICENSE
Requires-Dist: requests
Provides-Extra: test
Requires-Dist: tox ; extra == 'test'
